README.rst
setup.py
toyblock3.py
toyblock3.egg-info/PKG-INFO
toyblock3.egg-info/SOURCES.txt
toyblock3.egg-info/dependency_links.txt
toyblock3.egg-info/top_level.txt