Metadata-Version: 1.1
Name: toyblock3
Version: 1.1.0
Summary: A pythonic Entity-Component System written in pure Python
Home-page: https://github.com/dotoscat/toyblock3
Author: Oscar 'dotoscat' Triano
Author-email: UNKNOWN
License: LGPL-3.0
Keywords: development gamedev
Platform: UNKNOWN
Classifier: Development Status :: 5 - Production/Stable
Classifier: Intended Audience :: Developers
Classifier: License :: OSI Approved :: GNU Lesser General Public License v3 or later (LGPLv3+)
Classifier: Programming Language :: Python :: 3
